{
	"resultCount": 1,
	"results": [
		{
			"wrapperType": "track",
			"kind": "podcast",
			"artistId": 850139119,
			"collectionId": 788236947,
			"trackId": 788236947,
			"artistName": "Song Exploder",
			"collectionName": "Song Exploder",
			"trackName": "Song Exploder",
			"collectionCensoredName": "Song Exploder",
			"trackCensoredName": "Song Exploder",
			"artistViewUrl":
				"https://itunes.apple.com/us/artist/radiotopia/id850139119?mt=2&uo=4",
			"collectionViewUrl":
				"https://itunes.apple.com/us/podcast/song-exploder/id788236947?mt=2&uo=4",
			"feedUrl": "http://feed.songexploder.net/SongExploder",
			"trackViewUrl":
				"https://itunes.apple.com/us/podcast/song-exploder/id788236947?mt=2&uo=4",
			"artworkUrl30":
				"http://is3.mzstatic.com/image/thumb/Music128/v4/9e/28/35/9e283594-80c0-8cd2-d160-3346796d2ea7/source/30x30bb.jpg",
			"artworkUrl60":
				"http://is3.mzstatic.com/image/thumb/Music128/v4/9e/28/35/9e283594-80c0-8cd2-d160-3346796d2ea7/source/60x60bb.jpg",
			"artworkUrl100":
				"http://is3.mzstatic.com/image/thumb/Music128/v4/9e/28/35/9e283594-80c0-8cd2-d160-3346796d2ea7/source/100x100bb.jpg",
			"collectionPrice": 0.0,
			"trackPrice": 0.0,
			"trackRentalPrice": 0,
			"collectionHdPrice": 0,
			"trackHdPrice": 0,
			"trackHdRentalPrice": 0,
			"releaseDate": "2017-10-06T11:00:00Z",
			"collectionExplicitness": "cleaned",
			"trackExplicitness": "cleaned",
			"trackCount": 119,
			"country": "USA",
			"currency": "USD",
			"primaryGenreName": "Music",
			"contentAdvisoryRating": "Clean",
			"artworkUrl600":
				"http://is3.mzstatic.com/image/thumb/Music128/v4/9e/28/35/9e283594-80c0-8cd2-d160-3346796d2ea7/source/600x600bb.jpg",
			"genreIds": ["1310", "26"],
			"genres": ["Music", "Podcasts"]
		}
	]
}
